[1,["8cGSX6v91HjI6nl2WPODRZ"],0,[["sp.SkeletonData",["_name","_atlasText","textureNames","_skeletonJson","textures"],-1,3]],[[0,0,1,2,3,4,5]],[[0,"toushiche","\ntoushiche.png\nsize: 40,455\nformat: RGBA8888\nfilter: Linear,Linear\nrepeat: none\nhy\n  rotate: false\n  xy: 2, 277\n  size: 35, 41\n  orig: 37, 45\n  offset: 0, 2\n  index: -1\nhy1\n  rotate: false\n  xy: 2, 150\n  size: 34, 38\n  orig: 37, 45\n  offset: 1, 2\n  index: -1\nhy2\n  rotate: false\n  xy: 2, 233\n  size: 33, 42\n  orig: 37, 45\n  offset: 1, 2\n  index: -1\nhy3\n  rotate: false\n  xy: 2, 190\n  size: 34, 41\n  orig: 37, 45\n  offset: 1, 2\n  index: -1\nhy4\n  rotate: false\n  xy: 2, 409\n  size: 35, 44\n  orig: 37, 45\n  offset: 1, 1\n  index: -1\nhy5\n  rotate: false\n  xy: 2, 110\n  size: 34, 38\n  orig: 37, 45\n  offset: 1, 2\n  index: -1\nhy6\n  rotate: false\n  xy: 2, 365\n  size: 36, 42\n  orig: 37, 45\n  offset: 1, 2\n  index: -1\nhy7\n  rotate: false\n  xy: 2, 70\n  size: 35, 38\n  orig: 37, 45\n  offset: 1, 2\n  index: -1\nhy8\n  rotate: false\n  xy: 2, 320\n  size: 34, 43\n  orig: 37, 45\n  offset: 1, 2\n  index: -1\nhy9\n  rotate: false\n  xy: 2, 29\n  size: 33, 39\n  orig: 37, 45\n  offset: 0, 2\n  index: -1\nst\n  rotate: false\n  xy: 2, 2\n  size: 26, 25\n  orig: 26, 25\n  offset: 0, 0\n  index: -1\n",["toushiche.png"],{"skeleton":{"hash":"Z66wjJgEpcQKYDLK0VWCv/5gab0","spine":"3.8.75","x":-13,"y":-12.5,"width":26,"height":599,"images":"","audio":"E:/战争进化/陨石/陨石"},"bones":[{"name":"root"},{"name":"bone","parent":"root"},{"name":"bone2","parent":"root","x":-0.77,"y":11.01,"scaleX":0.7335},{"name":"bone57","parent":"root","y":574},{"name":"bone58","parent":"root","y":574},{"name":"bone59","parent":"root","y":574},{"name":"bone60","parent":"root","y":574},{"name":"bone61","parent":"root","y":574}],"slots":[{"name":"hy","bone":"bone2"},{"name":"st","bone":"bone","attachment":"st"},{"name":"st2","bone":"bone57","attachment":"st"},{"name":"st3","bone":"bone58","attachment":"st"},{"name":"st4","bone":"bone59","attachment":"st"},{"name":"st5","bone":"bone60","attachment":"st"},{"name":"st6","bone":"bone61","attachment":"st"}],"skins":[{"name":"default","attachments":{"hy":{"hy":{"x":0.62,"y":0.37,"width":37,"height":45},"hy1":{"x":0.44,"y":0.42,"width":37,"height":45},"hy2":{"x":0.44,"y":0.42,"width":37,"height":45},"hy3":{"x":0.44,"y":0.42,"width":37,"height":45},"hy4":{"x":0.44,"y":0.42,"width":37,"height":45},"hy5":{"x":0.44,"y":0.42,"width":37,"height":45},"hy6":{"x":0.44,"y":0.42,"width":37,"height":45},"hy7":{"x":0.44,"y":0.42,"width":37,"height":45},"hy8":{"x":0.44,"y":0.42,"width":37,"height":45},"hy9":{"x":0.44,"y":0.42,"width":37,"height":45}},"st":{"st":{"width":26,"height":25}},"st2":{"st":{"width":26,"height":25}},"st3":{"st":{"width":26,"height":25}},"st4":{"st":{"width":26,"height":25}},"st5":{"st":{"width":26,"height":25}},"st6":{"st":{"width":26,"height":25}}}}],"animations":{"animation1":{"slots":{"st3":{"attachment":[{"name":null}]},"st6":{"attachment":[{"name":null}]},"st2":{"attachment":[{"name":null}]},"st4":{"attachment":[{"name":null}]},"st5":{"attachment":[{"name":null}]}},"bones":{"bone":{"rotate":[{"angle":-179}]}}},"animation2":{"slots":{"st":{"attachment":[{"name":null}]},"hy":{"color":[{"color":"ffffff00"}],"attachment":[{"name":"hy"}]}},"bones":{"bone":{"rotate":[{"angle":-179}]},"bone2":{"translate":[{"y":12.1}],"scale":[{"x":0.49,"y":0.49}]},"bone57":{"rotate":[{},{"time":0.5,"angle":139.34}],"translate":[{"y":-574},{"time":0.1333,"x":-14.59,"y":-549.26},{"time":0.2333,"x":-20.54,"y":-546.88},{"time":0.3333,"x":-28.41,"y":-571.37},{"time":0.3667,"x":-29.12,"y":-569.94},{"time":0.4,"x":-30.79,"y":-572.44},{"time":0.5,"x":-30.79,"y":-573.87}],"scale":[{"x":0.5,"y":0.5}]},"bone58":{"rotate":[{},{"time":0.5,"angle":-156.58}],"translate":[{"y":-574},{"time":0.1333,"x":-9.46,"y":-557.79},{"time":0.2,"x":-13.03,"y":-557.55},{"time":0.3333,"x":-15.3,"y":-577.14},{"time":0.3667,"x":-19.36,"y":-574.03},{"time":0.4,"x":-20.07,"y":-576.41},{"time":0.5,"x":-20.07,"y":-578.07}],"scale":[{"x":0.3,"y":0.3}]},"bone59":{"rotate":[{},{"time":0.5,"angle":-156.58}],"translate":[{"y":-574},{"time":0.1333,"x":11.7,"y":-558.28},{"time":0.2,"x":13.37,"y":-559.83},{"time":0.3333,"x":16.82,"y":-573.04},{"time":0.4,"x":17.42,"y":-571.97},{"time":0.5,"x":18.37,"y":-573.28}],"scale":[{"x":0.3,"y":0.3}]},"bone60":{"rotate":[{},{"time":0.5,"angle":-156.58}],"translate":[{"y":-574},{"time":0.1333,"x":7.83,"y":-567.11},{"time":0.2,"x":9.14,"y":-566.04},{"time":0.3333,"x":11.16,"y":-573.9},{"time":0.4,"x":11.4,"y":-572.94},{"time":0.5,"x":12.23,"y":-574.73}],"scale":[{"x":0.2,"y":0.2}]},"bone61":{"rotate":[{},{"time":0.5,"angle":-130.7}],"translate":[{"y":-574},{"time":0.1333,"x":0.6,"y":-557.11},{"time":0.2,"x":0.6,"y":-555.8},{"time":0.3333,"x":-1.9,"y":-572.46},{"time":0.3667,"x":-2.25,"y":-571.74},{"time":0.4,"x":-2.25,"y":-572.46},{"time":0.5,"x":-2.25,"y":-574.12}],"scale":[{"x":0.372,"y":0.372}]}}},"animation3":{"slots":{"st":{"attachment":[{"name":null}]},"st2":{"attachment":[{"name":null}]},"st3":{"attachment":[{"name":null}]},"st6":{"attachment":[{"name":null}]},"hy":{"color":[{"time":0.1333,"color":"ffffffff"},{"time":0.7333,"color":"ffffff00"}],"attachment":[{"name":"hy"},{"time":0.0667,"name":"hy1"},{"time":0.1333,"name":"hy2"},{"time":0.2,"name":"hy3"},{"time":0.2667,"name":"hy4"},{"time":0.3333,"name":"hy5"},{"time":0.4,"name":"hy6"},{"time":0.4667,"name":"hy7"},{"time":0.5333,"name":"hy8"},{"time":0.6,"name":"hy9"},{"time":0.6667,"name":"hy"},{"time":0.7333,"name":"hy1"}]},"st4":{"attachment":[{"name":null}]},"st5":{"attachment":[{"name":null}]}},"bones":{"bone2":{"translate":[{"x":0.77,"y":3.97}],"scale":[{},{"time":0.7333,"x":0.735,"y":0.735}]}}}}},[0]]],0,0,[0],[-1],[0]]